panda3d_itchio/__init__.py
panda3d_itchio/launcher.py
panda3d_itchio/services.py
panda3d_itchio-1.1.0.dist-info/LICENSE
panda3d_itchio-1.1.0.dist-info/METADATA
panda3d_itchio-1.1.0.dist-info/WHEEL
panda3d_itchio-1.1.0.dist-info/top_level.txt
panda3d_itchio-1.1.0.dist-info/RECORD
