Metadata-Version: 2.1
Name: panda3d_itchio
Version: 1.1.0
Home-page: https://github.com/thetestgame/panda3d-itchio
Author: Jordan Maxwell
Maintainer: Jordan Maxwell
License: MIT
Classifier: Programming Language :: Python :: 3
License-File: LICENSE
Requires-Dist: panda3d
Requires-Dist: panda3d-rest
